SkypeURI/SkypeURI.py
SkypeURI/__init__.py
GOSH_FHIRworks2020_SkypeURI-1.0.0.dist-info/LICENSE
GOSH_FHIRworks2020_SkypeURI-1.0.0.dist-info/METADATA
GOSH_FHIRworks2020_SkypeURI-1.0.0.dist-info/WHEEL
GOSH_FHIRworks2020_SkypeURI-1.0.0.dist-info/top_level.txt
GOSH_FHIRworks2020_SkypeURI-1.0.0.dist-info/RECORD
