Metadata-Version: 2.1
Name: GOSH-FHIRworks2020-SkypeURI
Version: 1.0.0
Summary: GOSH FHIR Hackathon API
Home-page: https://github.com/AlexNiculae/GOSH-FHIRworks2020-SkypeURI
Author: Alexandru-Vlad Niculae
Author-email: 43644109+AlexNiculae@users.noreply.github.com
License: UNKNOWN
Platform: UNKNOWN
Classifier: Programming Language :: Python :: 3
Classifier: License :: OSI Approved :: MIT License
Classifier: Operating System :: OS Independent
Requires-Python: >=3.6
Requires-Dist: fhir-parser (>=0.1.5)
